radfx/__init__.py
radfx-0.0.1.dist-info/WHEEL
radfx-0.0.1.dist-info/METADATA
radfx-0.0.1.dist-info/RECORD
