Metadata-Version: 2.3
Name: radfx
Version: 0.0.1
Summary: Rapid Application Development framework for Python
Author: Your Name
License: Apache-2.0
Requires-Python: >=3.13
